tcpbridge/__init__.py
tcpbridge/sink.py
tcpbridge/tcp_bridge.py
tcpbridge/tcp_server.py
tcpbridge-1.1.1.dist-info/DESCRIPTION.rst
tcpbridge-1.1.1.dist-info/METADATA
tcpbridge-1.1.1.dist-info/RECORD
tcpbridge-1.1.1.dist-info/WHEEL
tcpbridge-1.1.1.dist-info/metadata.json
tcpbridge-1.1.1.dist-info/top_level.txt
