Metadata-Version: 2.0
Name: tcpbridge
Version: 1.1.1
Summary: UNKNOWN
Home-page: https://github.com/emlid/tcp-bridge
Author: Denis Chagin
Author-email: denis.chagin@emlid.com
License: UNKNOWN
Platform: UNKNOWN
Provides-Extra: test
Requires-Dist: pytest; extra == 'test'
Requires-Dist: pytest-cov; extra == 'test'
